hexintcalc/LICENSE
hexintcalc/README.MD
hexintcalc/__init__.py
hexintcalc/requirements.txt
hexintcalc/thirdparty.json
hexintcalc-0.10.dist-info/LICENSE.rst
hexintcalc-0.10.dist-info/METADATA
hexintcalc-0.10.dist-info/WHEEL
hexintcalc-0.10.dist-info/top_level.txt
hexintcalc-0.10.dist-info/RECORD
